README.md
setup.py
bredon/__init__.py
bredon/__main__.py
bredon.egg-info/PKG-INFO
bredon.egg-info/SOURCES.txt
bredon.egg-info/dependency_links.txt
bredon.egg-info/requires.txt
bredon.egg-info/top_level.txt
bredon/controller/__init__.py
bredon/model/__init__.py
bredon/model/notation.py
bredon/model/player.py
bredon/model/utils/__init__.py
bredon/model/utils/constants.py
bredon/neural/__init__.py
bredon/neural/automl.py
bredon/neural/coerce.py
bredon/neural/download.py
bredon/neural/ptn_to_csv.py
bredon/reinforcement/__init__.py
bredon/reinforcement/actions.py
bredon/reinforcement/agent.py
bredon/reinforcement/env.py
bredon/reinforcement/new_agent.py
bredon/tests/__init__.py
bredon/tests/test_ai.py
bredon/tests/test_road.py
bredon/view/__init__.py