Metadata-Version: 2.1
Name: bredon
Version: 1.0.4
Summary: A set of tools for the game Tak.
Home-page: https://github.com/Innoviox/bredon
Author: Simon Chervenak
Author-email: simonlcherv@gmail.com
License: GNU General Public License v3.0
Platform: UNKNOWN
